<?xml version="1.0" encoding="UTF-8"?>

<!-- 
/*
 * Copyright 2001-2004 The Apache Software Foundation.
 * 
 * Licensed under the Apache License, Version 2.0 (the "License");
 * you may not use this file except in compliance with the License.
 * You may obtain a copy of the License at
 * 
 *      http://www.apache.org/licenses/LICENSE-2.0
 * 
 * Unless required by applicable law or agreed to in writing, software
 * distributed under the License is distributed on an "AS IS" BASIS,
 * WITHOUT WARRANTIES OR CONDITIONS OF ANY KIND, either express or implied.
 * See the License for the specific language governing permissions and
 * limitations under the License.
 */
 -->

<document>
  <properties>
    <title>Changes</title>
    <author email="dion@apache.org">dIon Gillard</author>
  </properties>
  <body>
    <release version="1.1-SNAPSHOT" date="in CVS">
      <action dev="dion" type="add" issue="JELLY-59" due-to="Bill Keese">multi-part mime http request</action>
      <action dev="dion" type="fix" issue="JELLY-96" due-to="Jason Horne">HttpClient cannot be specified in HttpSession</action>
    </release>
    <release version="1.0" date="2004-09-12"></release>
  </body>
</document>
